dualite_transnumerique/VERSION
dualite_transnumerique/__init__.py
dualite_transnumerique/acces.py
dualite_transnumerique/afficheur.py
dualite_transnumerique/aleatoire1120.txt.gz
dualite_transnumerique/aleatoire1M.txt.gz
dualite_transnumerique/aleatoire300K.txt.gz
dualite_transnumerique/algo.py
dualite_transnumerique/calcul.py
dualite_transnumerique/entree.py
dualite_transnumerique/erreur.py
dualite_transnumerique/fenetre.ui
dualite_transnumerique/shell.py
dualite_transnumerique/ui.py
dualite_transnumerique-0.3.0.data/data/VERSION
dualite_transnumerique-0.3.0.data/data/aleatoire1120.txt.gz
dualite_transnumerique-0.3.0.data/data/aleatoire1M.txt.gz
dualite_transnumerique-0.3.0.data/data/aleatoire300K.txt.gz
dualite_transnumerique-0.3.0.data/data/fenetre.ui
dualite_transnumerique-0.3.0.dist-info/METADATA
dualite_transnumerique-0.3.0.dist-info/RECORD
dualite_transnumerique-0.3.0.dist-info/WHEEL
dualite_transnumerique-0.3.0.dist-info/entry_points.txt
dualite_transnumerique-0.3.0.dist-info/top_level.txt
