Metadata-Version: 2.1
Name: dualite-transnumerique
Version: 0.3.0
Summary: La dualité transnumérique
Home-page: http://n-interaction.ch
Author: Camptocamp
Author-email: info@camptocamp.com
License: UNKNOWN
Keywords: math
Platform: UNKNOWN
Classifier: Programming Language :: Python
Classifier: Programming Language :: Python :: 3.6
Requires-Dist: PyQt5 (==5.10.1)
